intently_nlu/__about__.py
intently_nlu/__init__.py
intently_nlu/__main__.py
intently_nlu/constants.py
intently_nlu/exceptions.py
intently_nlu/builtin_entities/__init__.py
intently_nlu/builtin_entities/number.py
intently_nlu/cli/__init__.py
intently_nlu/cli/cleanup.py
intently_nlu/cli/download.py
intently_nlu/cli/generate_dataset.py
intently_nlu/cli/inference.py
intently_nlu/cli/training.py
intently_nlu/cli/versions.py
intently_nlu/dataset/dataset.py
intently_nlu/dataset/entity.py
intently_nlu/dataset/intent.py
intently_nlu/entity_parsers/__init__.py
intently_nlu/entity_parsers/crf_entity_parser.py
intently_nlu/entity_parsers/deterministic_entity_parser.py
intently_nlu/entity_parsers/entity_parser.py
intently_nlu/intent_classifier/__init__.py
intently_nlu/intent_classifier/deterministic_intent_classifier.py
intently_nlu/intent_classifier/fuzzy_intent_classifier.py
intently_nlu/intent_classifier/intent_classifier.py
intently_nlu/nlu_engine/__init__.py
intently_nlu/nlu_engine/nlu_engine.py
intently_nlu/nlu_engine/nlu_engine_config.py
intently_nlu/nlu_engine/nlu_result.py
intently_nlu/util/intently_logging.py
intently_nlu/util/language.py
intently_nlu/util/ml_training.py
intently_nlu/util/normalization.py
intently_nlu/util/representation.py
intently_nlu/util/resources.py
intently_nlu/util/decorators/timing.py
intently_nlu/util/decorators/training.py
intently_nlu-0.0.3.dist-info/METADATA
intently_nlu-0.0.3.dist-info/WHEEL
intently_nlu-0.0.3.dist-info/licenses/LICENSE
intently_nlu-0.0.3.dist-info/RECORD
