Metadata-Version: 2.4
Name: intently-nlu
Version: 0.0.3
Summary: Python library to extract intention and structured information from sentences written in natural language.
Project-URL: Homepage, https://encrystudio.github.io/intently-nlu
Project-URL: Documentation, https://encrystudio.github.io/intently-nlu
Project-URL: Issues, https://github.com/encrystudio/intently-nlu/issues
Project-URL: Source, https://github.com/encrystudio/intently-nlu
Author-email: encrystudio <epfl.business+py@proton.me>, Clement Doumouro <clement.doumouro@snips.ai>, Adrien Ball <adrien.ball@snips.ai>
License-Expression: Apache-2.0
License-File: LICENSE
Classifier: Development Status :: 2 - Pre-Alpha
Classifier: Intended Audience :: Developers
Classifier: License :: OSI Approved :: MIT License
Classifier: Natural Language :: English
Classifier: Operating System :: Microsoft :: Windows
Classifier: Operating System :: POSIX :: Linux
Classifier: Programming Language :: Python
Classifier: Programming Language :: Python :: 3.10
Classifier: Programming Language :: Python :: 3.11
Classifier: Programming Language :: Python :: 3.12
Classifier: Programming Language :: Python :: 3.13
Classifier: Programming Language :: Python :: Implementation :: CPython
Classifier: Programming Language :: Python :: Implementation :: PyPy
Classifier: Topic :: Home Automation
Classifier: Topic :: Scientific/Engineering :: Artificial Intelligence
Classifier: Topic :: Scientific/Engineering :: Information Analysis
Classifier: Topic :: Text Processing
Classifier: Topic :: Text Processing :: Linguistic
Classifier: Topic :: Utilities
Classifier: Typing :: Typed
Requires-Python: >=3.10
Requires-Dist: dill~=0.3.9
Requires-Dist: platformdirs~=4.3.8
Requires-Dist: pyaml~=25.5.0
Requires-Dist: rapidfuzz~=3.13.0
Requires-Dist: requests~=2.32.4
Requires-Dist: sklearn-crfsuite>=0.5.0
